ssite/__init__.py
ssite/blog.py
ssite/clean.py
ssite/cli.py
ssite/header.py
ssite/hentry.py
ssite/index.py
ssite/note.py
ssite/rmblock.py
ssite/syndicate/__init__.py
ssite/syndicate/cli.py
ssite/syndicate/rss.py
ssite-0.4.0.dist-info/METADATA
ssite-0.4.0.dist-info/RECORD
ssite-0.4.0.dist-info/WHEEL
ssite-0.4.0.dist-info/entry_points.txt
ssite-0.4.0.dist-info/top_level.txt
